weightedpca/__init__.py
weightedpca/weighted_pca.py
weightedpca-0.1.0.dist-info/licenses/LICENSE
weightedpca-0.1.0.dist-info/METADATA
weightedpca-0.1.0.dist-info/WHEEL
weightedpca-0.1.0.dist-info/top_level.txt
weightedpca-0.1.0.dist-info/RECORD
