Metadata-Version: 2.4
Name: weightedpca
Version: 0.1.0
Summary: Weighted Principal Component Analysis
Author: Chris J.
License: BSD-3-Clause
Project-URL: Homepage, https://github.com/byoungj/weightedpca
Project-URL: Repository, https://github.com/byoungj/weightedpca
Project-URL: Issues, https://github.com/byoungj/weightedpca/issues
Keywords: pca,weighted,dimensionality-reduction,machine-learning
Classifier: Development Status :: 3 - Alpha
Classifier: Intended Audience :: Science/Research
Classifier: License :: OSI Approved :: BSD License
Classifier: Operating System :: OS Independent
Classifier: Programming Language :: Python :: 3
Classifier: Programming Language :: Python :: 3.9
Classifier: Programming Language :: Python :: 3.10
Classifier: Programming Language :: Python :: 3.11
Classifier: Programming Language :: Python :: 3.12
Classifier: Topic :: Scientific/Engineering
Requires-Python: >=3.9
License-File: LICENSE
Requires-Dist: numpy>=1.20
Requires-Dist: scipy>=1.6
Requires-Dist: scikit-learn>=1.0
Provides-Extra: dev
Requires-Dist: pytest>=7.0; extra == "dev"
Requires-Dist: pytest-cov>=4.0; extra == "dev"
Dynamic: license-file
